naas_abi/__init__.py
naas_abi/cli.py
naas_abi/agents/AbiAgent.py
naas_abi/agents/AbiAgent_test.py
naas_abi/agents/EntitytoSPARQLAgent.py
naas_abi/agents/EntitytoSPARQLAgent_test.py
naas_abi/agents/KnowledgeGraphBuilderAgent.py
naas_abi/agents/KnowledgeGraphBuilderAgent_test.py
naas_abi/agents/OntologyEngineerAgent.py
naas_abi/agents/OntologyEngineerAgent_test.py
naas_abi/apps/oxigraph_admin/main.py
naas_abi/apps/oxigraph_admin/terminal_style.py
naas_abi/apps/sparql_terminal/main.py
naas_abi/apps/sparql_terminal/terminal_style.py
naas_abi/models/airgap_gemma.py
naas_abi/models/airgap_qwen.py
naas_abi/models/default.py
naas_abi/pipelines/AIAgentOntologyGenerationPipeline.py
naas_abi/pipelines/AIAgentOntologyGenerationPipeline_test.py
naas_abi/pipelines/AddIndividualPipeline.py
naas_abi/pipelines/AddIndividualPipeline_test.py
naas_abi/pipelines/InsertDataSPARQLPipeline.py
naas_abi/pipelines/InsertDataSPARQLPipeline_test.py
naas_abi/pipelines/MergeIndividualsPipeline.py
naas_abi/pipelines/MergeIndividualsPipeline_test.py
naas_abi/pipelines/RemoveIndividualPipeline.py
naas_abi/pipelines/RemoveIndividualPipeline_test.py
naas_abi/pipelines/UpdateCommercialOrganizationPipeline.py
naas_abi/pipelines/UpdateDataPropertyPipeline.py
naas_abi/pipelines/UpdateLegalNamePipeline.py
naas_abi/pipelines/UpdateLinkedInPagePipeline.py
naas_abi/pipelines/UpdatePersonPipeline.py
naas_abi/pipelines/UpdateSkillPipeline.py
naas_abi/pipelines/UpdateTickerPipeline.py
naas_abi/pipelines/UpdateWebsitePipeline.py
naas_abi/workflows/AgentRecommendationWorkflow.py
naas_abi/workflows/AgentRecommendationWorkflow_test.py
naas_abi/workflows/ArtificialAnalysisWorkflow.py
naas_abi/workflows/ArtificialAnalysisWorkflow_test.py
naas_abi/workflows/GetObjectPropertiesFromClassWorkflow.py
naas_abi/workflows/GetObjectPropertiesFromClassWorkflow_test.py
naas_abi/workflows/GetSubjectGraphWorkflow.py
naas_abi/workflows/GetSubjectGraphWorkflow_test.py
naas_abi/workflows/SearchIndividualWorkflow.py
naas_abi-1.0.14.dist-info/METADATA
naas_abi-1.0.14.dist-info/WHEEL
naas_abi-1.0.14.dist-info/top_level.txt
naas_abi-1.0.14.dist-info/RECORD
