Metadata-Version: 2.4
Name: naas-abi
Version: 1.0.14
Summary: Multi-agent orchestrator and knowledge graph management system for AI orchestration, providing comprehensive coordination of specialized AI agents and semantic data management capabilities
Author-email: Maxime Jublou <maxime@naas.ai>, Florent Ravenel <florent@naas.ai>, Jeremy Ravenel <jeremy@naas.ai>
License: MIT License
Project-URL: Homepage, https://github.com/jupyter-naas/abi
Project-URL: Repository, https://github.com/jupyter-naas/abi/tree/main/libs/naas-abi
Requires-Python: <4,>=3.10
Requires-Dist: naas-abi-core>=1.4.0
Requires-Dist: naas-abi-marketplace>=1.3.3
Requires-Dist: thefuzz>=0.22.1
